{
  "Changes": [
    {
      "Action": "EditData",
      "Target": "Data/Shops",
      "TargetField": [
        "QiGemShop",
        "Items"
      ],
      "Entries": {
        "{{ModId}}.Test": {
          "TradeItemId": "(O)858",
          "TradeItemAmount": 50,
          "Price": -1,
          "ApplyProfitMargins": null,
          "AvailableStock": -1,
          "AvailableStockLimit": "Global",
          "AvoidRepeat": false,
          "UseObjectDataPrice": false,
          "IgnoreShopPriceModifiers": false,
          "PriceModifiers": null,
          "PriceModifierMode": "Stack",
          "AvailableStockModifiers": null,
          "AvailableStockModifierMode": "Stack",
          "Condition": null,
          "Id": "(BC){{ModId}}.Irradiator (Recipe)",
          "ItemId": "(BC){{ModId}}.Irradiator",
          "RandomItemId": null,
          "MaxItems": null,
          "MinStack": -1,
          "MaxStack": -1,
          "Quality": -1,
          "ObjectInternalName": null,
          "ObjectDisplayName": null,
          "ToolUpgradeLevel": -1,
          "IsRecipe": true,
          "StackModifiers": null,
          "StackModifierMode": "Stack",
          "QualityModifiers": null,
          "QualityModifierMode": "Stack",
          "ModData": null,
          "PerItemCondition": null
        }
      }
    }
  ]
}